LICENSE
MANIFEST.in
README.md
setup.cfg
setup.py
ajaxview/__init__.py
ajaxview/exceptions.py
ajaxview/templates/ajax_headers.html
django_ajaxview.egg-info/PKG-INFO
django_ajaxview.egg-info/SOURCES.txt
django_ajaxview.egg-info/dependency_links.txt
django_ajaxview.egg-info/requires.txt
django_ajaxview.egg-info/top_level.txt
docs/changelog.md
docs/index.md
docs/installation.md
docs/usage-greeting-error.png
docs/usage-greeting.png
docs/usage.md